harnice/__init__.py
harnice/__main__.py
harnice/cli.py
harnice/fileio.py
harnice/state.py
harnice/gui/launcher.py
harnice/lists/channel_map.py
harnice/lists/circuits_list.py
harnice/lists/disconnect_map.py
harnice/lists/formboard_graph.py
harnice/lists/instances_list.py
harnice/lists/library_history.py
harnice/lists/manifest.py
harnice/lists/post_harness_instances_list.py
harnice/lists/rev_history.py
harnice/lists/signals_list.py
harnice/products/__init__.py
harnice/products/cable.py
harnice/products/chtype.py
harnice/products/device.py
harnice/products/disconnect.py
harnice/products/flagnote.py
harnice/products/harness.py
harnice/products/macro.py
harnice/products/part.py
harnice/products/system.py
harnice/products/tblock.py
harnice/utils/appearance.py
harnice/utils/circuit_utils.py
harnice/utils/feature_tree_utils.py
harnice/utils/formboard_utils.py
harnice/utils/library_utils.py
harnice/utils/note_utils.py
harnice/utils/svg_utils.py
harnice/utils/system_utils.py
harnice-0.3.0.dist-info/licenses/LICENSE
harnice-0.3.0.dist-info/METADATA
harnice-0.3.0.dist-info/WHEEL
harnice-0.3.0.dist-info/entry_points.txt
harnice-0.3.0.dist-info/top_level.txt
harnice-0.3.0.dist-info/RECORD
