Metadata-Version: 2.4
Name: harnice
Version: 0.3.0
Summary: Electrical System CAD
Author-email: Kenyon Shutt <harnice.io@gmail.com>
Project-URL: Documentation, https://harnice.io/
Project-URL: Homepage, https://github.com/harnice/Harnice
Project-URL: Issues, https://github.com/harnice/Harnice/issues
Classifier: Programming Language :: Python :: 3
Classifier: License :: OSI Approved :: MIT License
Classifier: Operating System :: OS Independent
Requires-Python: >=3.8
License-File: LICENSE
Requires-Dist: PySide6>=6.6
Requires-Dist: sexpdata
Requires-Dist: Pillow
Requires-Dist: PyYAML
Requires-Dist: xlwt
Requires-Dist: webcolors
Dynamic: license-file
